ztensor-1.1.1.dist-info/METADATA
ztensor-1.1.1.dist-info/WHEEL
ztensor-1.1.1.dist-info/licenses/LICENSE
ztensor/__init__.py
ztensor/numpy.py
ztensor/torch.py
ztensor/ztensor/__init__.py
ztensor/ztensor/ffi.py
ztensor/ztensor/libztensor.so
ztensor-1.1.1.dist-info/RECORD
