Metadata-Version: 2.4
Name: ztensor
Version: 1.1.1
Classifier: Programming Language :: Rust
Classifier: Programming Language :: Python :: 3
Classifier: License :: OSI Approved :: MIT License
Classifier: Operating System :: OS Independent
Classifier: Intended Audience :: Developers
Classifier: Topic :: Scientific/Engineering
Requires-Dist: numpy
Requires-Dist: cffi
Requires-Dist: ml-dtypes
License-File: LICENSE
Summary: Python bindings for the zTensor library.
Author-email: In Gim <in.gim@yale.edu>
License-Expression: MIT
Project-URL: Homepage, https://github.com/pie-project/ztensor
Project-URL: Source, https://github.com/pie-project/ztensor
